firebird/__init__.py
firebird/base.py
firebird/core_apis.py
firebird/rabbitmq.py
firebird/zkdb.py
firebird/cmd_tools/__init__.py
firebird/cmd_tools/executor.py
firebird/cmd_tools/executor_impl.py
firebird/cmd_tools/fbconsole.py
firebird/cmd_tools/pipeline.py
firebird/libs/__init__.py
firebird/libs/k8.py
firebird/libs/template.py
firebird/resources/templates/pipeline.yaml
firebirdconsole/__init__.py
firebirdconsole/firebirdconsole/__init__.py
firebirdconsole/firebirdconsole/asgi.py
firebirdconsole/firebirdconsole/patch_request_middleware.py
firebirdconsole/firebirdconsole/settings.py
firebirdconsole/firebirdconsole/urls.py
firebirdconsole/firebirdconsole/wsgi.py
firebirdconsole/ui/__init__.py
firebirdconsole/ui/admin.py
firebirdconsole/ui/apps.py
firebirdconsole/ui/models.py
firebirdconsole/ui/tests.py
firebirdconsole/ui/urls.py
firebirdconsole/ui/view_tools.py
firebirdconsole/ui/migrations/__init__.py
firebirdconsole/ui/static/images/logo.jpeg
firebirdconsole/ui/static/js-bundle/home.js
firebirdconsole/ui/static/js-bundle/home.js.LICENSE.txt
firebirdconsole/ui/static/js-bundle/pipeline.js
firebirdconsole/ui/static/js-bundle/pipeline.js.LICENSE.txt
firebirdconsole/ui/templates/application.html
firebirdconsole/ui/templates/index.html
firebirdconsole/ui/templatetags/__init__.py
firebirdconsole/ui/templatetags/app_filters.py
firebirdconsole/ui/views/__init__.py
firebirdconsole/ui/views/home.py
firebirdconsole/ui/views/pipeline.py
firebirdconsole/ui/views/apis/__init__.py
firebirdconsole/ui/views/apis/api_base.py
firebirdconsole/ui/views/apis/main.py
pyfirebird-0.0.115.dist-info/METADATA
pyfirebird-0.0.115.dist-info/WHEEL
pyfirebird-0.0.115.dist-info/entry_points.txt
pyfirebird-0.0.115.dist-info/top_level.txt
pyfirebird-0.0.115.dist-info/RECORD
