Metadata-Version: 2.1
Name: pyfirebird
Version: 0.0.115
Summary: Streaming Data Processing Framework
Home-page: https://github.com/stonezhong/firebird
Author: Stone Zhong
Author-email: stonezhong@hotmail.com
License: MIT
Classifier: License :: OSI Approved :: MIT License
Classifier: Programming Language :: Python :: 3
Requires-Dist: pika
Requires-Dist: kazoo
Requires-Dist: Django (>=4.2.1)
Requires-Dist: mysqlclient
Requires-Dist: graphviz (>=0.20.1)
Requires-Dist: kubernetes
Requires-Dist: Jinja2
